[{"family":"MaterialIcons","fonts":[{"asset":"fonts/MaterialIcons-Regular.otf"}]},{"family":"AveriaSerifLibre","fonts":[{"asset":"assets/fonts/Averia%20Serif%20Libre/AveriaSerifLibre-Bold.ttf"},{"asset":"assets/fonts/Averia%20Serif%20Libre/AveriaSerifLibre-BoldItalic.ttf"},{"asset":"assets/fonts/Averia%20Serif%20Libre/AveriaSerifLibre-Italic.ttf"},{"asset":"assets/fonts/Averia%20Serif%20Libre/AveriaSerifLibre-Light.ttf"},{"asset":"assets/fonts/Averia%20Serif%20Libre/AveriaSerifLibre-LightItalic.ttf"},{"asset":"assets/fonts/Averia%20Serif%20Libre/AveriaSerifLibre-Regular.ttf"}]},{"family":"packages/cupertino_icons/CupertinoIcons","fonts":[{"asset":"packages/cupertino_icons/assets/CupertinoIcons.ttf"}]}]